appserver
broadwick
examples
workflow
