Metadata-Version: 1.0
Name: broadwick
Version: 1.1.0
Summary: A Python Application Environment.
Home-page: http://launchpad.net/broadwick
Author: Peter Bunyan, Jonathan Marshall, Petra Chong
Author-email: UNKNOWN
License: UNKNOWN
Platform: UNKNOWN
